pycollage/__init__.py
pycollage/processing.py
pycollage-0.0.0.dist-info/METADATA
pycollage-0.0.0.dist-info/WHEEL
pycollage-0.0.0.dist-info/entry_points.txt
pycollage-0.0.0.dist-info/top_level.txt
pycollage-0.0.0.dist-info/RECORD
