Metadata-Version: 2.1
Name: pycollage
Version: 0.0.0
Summary: Recreate an image with many others
Home-page: https://github.com/kklein/pycollage
Author: kklein
Classifier: Programming Language :: Python :: 3
Classifier: Programming Language :: Python :: 3.8
Classifier: Programming Language :: Python :: 3.9
Classifier: Programming Language :: Python :: 3.10
Requires-Python: >=3.8
Requires-Dist: annoy
Requires-Dist: pillow
Requires-Dist: click
